twosampyle/__init__.py
twosampyle/permchisquare.py
twosampyle/permtest.py
twosampyle/plot_utils.py
twosampyle/ttest.py
twosampyle/twosampyle_utils.py
twosampyle-0.1.87.dist-info/DESCRIPTION.rst
twosampyle-0.1.87.dist-info/METADATA
twosampyle-0.1.87.dist-info/RECORD
twosampyle-0.1.87.dist-info/WHEEL
twosampyle-0.1.87.dist-info/metadata.json
twosampyle-0.1.87.dist-info/top_level.txt
