Metadata-Version: 2.0
Name: twosampyle
Version: 0.1.87
Summary: Python module for two-sample statistical tests
Home-page: https://github.com/jwilber/twosampyle
Author: Jared Wilber
Author-email: jdwlbr@gmail.com
License: GNU3
Platform: UNKNOWN
Requires-Dist: matplotlib
Requires-Dist: numpy
Requires-Dist: pandas
Requires-Dist: scipy
